[
  {
    "PROPER_NAME": "Snekproof",
    "NAMES": [
      "snekproof" //Змеккогнор || Противозмекковая
    ],
    "DESCRIPTION": "На #yПротивозмекковые карты не влияет #yЗамешательство и они не могут быть #yСпутаны."
  },
  {
    "PROPER_NAME": "Спутывание",
    "NAMES": [
      "спутывание",
      "спутывает",
      "спутанная",
      "спутанные",
      "спутанную",
      "спутаны",
      "спутываете"
    ],
    "DESCRIPTION": "Меняет стоимость карты до конца хода на случайную, от #b0 до #b3."
  },
  {
    "PROPER_NAME": "Внеклассовые карты",
    "NAMES": [
      "внеклассовые карты",
      "внеклассовая",
      "внеклассовую",
      "внеклассовый"
    ],
    "DESCRIPTION": "#yВнеклассовые карты - любые получаемые карты отличные от вашего цвета ( Включая #yБесцветные, #yПроклятия и #yСтатусы )."
  },
  {
    "PROPER_NAME": "Identify",
    "NAMES": [
      "identify"
    ],
    "DESCRIPTION": "Навсегда заменяет #yНеизвестные карты на те, которыми они являются на данный момент."
  },
  {
    "PROPER_NAME": "Везение",
    "NAMES": [
      "везение",
      "везения"
    ],
    "DESCRIPTION": "Карты, которые выбирают случайное число, будут выбирать максимально возможное. ( Не влияет на #yСпутывание. )"
  }
]